{
  "package": "com.ruixin.huawei",
  "device": "5SM0125606000291",
  "ability": "EntryAbility",
  "n": 8,
  "wait_s": 10.0,
  "blank_threshold": 0.92,
  "blank_count": 5,
  "blank_rate": "5/8",
  "blank_rate_pct": 62.5,
  "bug_if_blank": true,
  "classification": "SUT reliability bug: intermittent blank white cold start (FOREGROUND, no UI paint)",
  "trials": [
    {
      "trial": 0,
      "wait_s": 10.0,
      "white_frac": 0.2549,
      "mean_pixel": 207.81,
      "foreground": true,
      "blank": false,
      "screenshot": "cold-start/trial_00.png"
    },
    {
      "trial": 1,
      "wait_s": 10.0,
      "white_frac": 0.9854,
      "mean_pixel": 249.49,
      "foreground": true,
      "blank": true,
      "screenshot": "cold-start/trial_01.png"
    },
    {
      "trial": 2,
      "wait_s": 10.0,
      "white_frac": 0.9854,
      "mean_pixel": 249.49,
      "foreground": true,
      "blank": true,
      "screenshot": "cold-start/trial_02.png"
    },
    {
      "trial": 3,
      "wait_s": 10.0,
      "white_frac": 0.2549,
      "mean_pixel": 207.81,
      "foreground": true,
      "blank": false,
      "screenshot": "cold-start/trial_03.png"
    },
    {
      "trial": 4,
      "wait_s": 10.0,
      "white_frac": 0.9854,
      "mean_pixel": 249.49,
      "foreground": true,
      "blank": true,
      "screenshot": "cold-start/trial_04.png"
    },
    {
      "trial": 5,
      "wait_s": 10.0,
      "white_frac": 0.2622,
      "mean_pixel": 212.75,
      "foreground": true,
      "blank": false,
      "screenshot": "cold-start/trial_05.png"
    },
    {
      "trial": 6,
      "wait_s": 10.0,
      "white_frac": 0.9854,
      "mean_pixel": 249.49,
      "foreground": true,
      "blank": true,
      "screenshot": "cold-start/trial_06.png"
    },
    {
      "trial": 7,
      "wait_s": 10.0,
      "white_frac": 0.9854,
      "mean_pixel": 249.49,
      "foreground": true,
      "blank": true,
      "screenshot": "cold-start/trial_07.png"
    }
  ]
}